bihc/__init__.py
bihc/beam.py
bihc/fillingschemes.py
bihc/impedance.py
bihc/plot.py
bihc/power.py
bihc-0.0.8.10.dist-info/LICENSE
bihc-0.0.8.10.dist-info/METADATA
bihc-0.0.8.10.dist-info/WHEEL
bihc-0.0.8.10.dist-info/top_level.txt
bihc-0.0.8.10.dist-info/RECORD
