Metadata-Version: 2.1
Name: bihc
Version: 0.0.8.10
Summary: BIHC: Beam-Induced Heating Computation package
Home-page: https://github.com/LeonardoSito/BIHC
Author: Elena de la Fuente, Francesco Giordano, Leonardo Sito
Author-email: benoit.salvant@cern.ch
Project-URL: Bug Tracker, https://github.com/LeonardoSito/BIHC/issues
Classifier: Development Status :: 3 - Alpha
Classifier: Intended Audience :: Developers
Classifier: Natural Language :: English
Classifier: Programming Language :: Python :: 3
Classifier: Operating System :: OS Independent
License-File: LICENSE
Requires-Dist: numpy
Requires-Dist: matplotlib
Requires-Dist: scipy
